LICENSE
MANIFEST.in
README.md
requirements.txt
setup.py
panelbeater/__init__.py
panelbeater/__main__.py
panelbeater/copula.py
panelbeater/download.py
panelbeater/features.py
panelbeater/fit.py
panelbeater/kelly.py
panelbeater/normalizer.py
panelbeater/options.py
panelbeater/simulate.py
panelbeater/sizing.py
panelbeater/sync.py
panelbeater/trades.py
panelbeater/wt.py
panelbeater.egg-info/PKG-INFO
panelbeater.egg-info/SOURCES.txt
panelbeater.egg-info/dependency_links.txt
panelbeater.egg-info/entry_points.txt
panelbeater.egg-info/not-zip-safe
panelbeater.egg-info/requires.txt
panelbeater.egg-info/top_level.txt
tests/__init__.py
tests/test_features.py
tests/test_kelly.py
tests/test_normalizer.py
tests/test_options.py
tests/test_sizing.py
tests/test_sync.py
tests/test_trades_integration.py