Metadata-Version: 2.1
Name: panelbeater
Version: 0.2.46
Summary: A CLI for finding mispriced options.
Home-page: https://github.com/8W9aG/panelbeater
Author: Will Sackfield
Author-email: will.sackfield@gmail.com
License: MIT
Keywords: options
Classifier: License :: OSI Approved :: MIT License
Classifier: Programming Language :: Python :: 3
License-File: LICENSE
Requires-Dist: yfinance==0.2.66
Requires-Dist: pandas>=2.3.3
Requires-Dist: pandas-datareader>=0.10.0
Requires-Dist: numpy>=2.2.6
Requires-Dist: feature-engine>=1.9.3
Requires-Dist: requests-cache>=1.2.1
Requires-Dist: scikit-learn>=1.6.1
Requires-Dist: wavetrainer>=0.3.10
Requires-Dist: tqdm>=4.67.1
Requires-Dist: pyvinecopulib>=0.7.5
Requires-Dist: fredapi>=0.5.2
Requires-Dist: python-dotenv>=1.1.0
Requires-Dist: kaleido>=1.2.0
Requires-Dist: plotly>=6.3.1
Requires-Dist: scipy>=1.16.3
Requires-Dist: joblib>=1.5.2
Requires-Dist: pyarrow>=22.0.0
Requires-Dist: alpaca-py>=0.43.2
